{
  "font": "Lucida Grande",
  "font_size": 12,
  "text_color": [
    255,
    255,
    255,
    255
  ],
  "gui_color": [
    255,
    0,
    0,
    255
  ],
  "slider": {
    "knob": {
      "image": {
        "source": "slider-knob.png"
      },
      "offset": [
        -5,
        -11
      ]
    },
    "padding": [
      8,
      8,
      8,
      8
    ],
    "step": {
      "image": {
        "source": "slider-step.png"
      },
      "offset": [
        -2,
        -8
      ]
    },
    "bar": {
      "image": {
        "source": "slider-bar.png",
        "frame": [
          8,
          8,
          8,
          0
        ],
        "padding": [
          8,
          8,
          8,
          8
        ]
      }
    }
  }
}